ScoreDraft/BasicSamplers.dll
ScoreDraft/BasicSamplers.py
ScoreDraft/CVVCChineseConverter.py
ScoreDraft/Catalog.py
ScoreDraft/Document.py
ScoreDraft/Initializers.py
ScoreDraft/Instrument.py
ScoreDraft/JPVCVConverter.py
ScoreDraft/KarplusStrong.dll
ScoreDraft/KarplusStrong.py
ScoreDraft/MIDIWriter.dll
ScoreDraft/MIDIWriter.py
ScoreDraft/Meteor.dll
ScoreDraft/Meteor.py
ScoreDraft/MusicXMLDocument.py
ScoreDraft/Notes.py
ScoreDraft/PCMPlayer.dll
ScoreDraft/PCMPlayer.py
ScoreDraft/Percussion.py
ScoreDraft/RapChinese.py
ScoreDraft/ScoreDraftCore.dll
ScoreDraft/ScoreDraftCore.py
ScoreDraft/SimpleInstruments.dll
ScoreDraft/SimpleInstruments.py
ScoreDraft/Singer.py
ScoreDraft/SoundFont2.dll
ScoreDraft/SoundFont2.py
ScoreDraft/TTEnglishConverter.py
ScoreDraft/TTLyricSet.data
ScoreDraft/TsuroVCVConverter.py
ScoreDraft/UTAUUtils.py
ScoreDraft/UtauDraft.py
ScoreDraft/VCCVEnglishConverter.py
ScoreDraft/VCCVLyricSet.data
ScoreDraft/VoiceSampler.dll
ScoreDraft/VoiceSampler.py
ScoreDraft/XiaYYConverter.py
ScoreDraft/YAMLDocument.py
ScoreDraft/__init__.py
ScoreDraft/libBasicSamplers.so
ScoreDraft/libKarplusStrong.so
ScoreDraft/libMIDIWriter.so
ScoreDraft/libMeteor.so
ScoreDraft/libPCMPlayer.so
ScoreDraft/libScoreDraftCore.so
ScoreDraft/libSimpleInstruments.so
ScoreDraft/libSoundFont2.so
ScoreDraft/libVoiceSampler.so
ScoreDraft/musicxml/__init__.py
ScoreDraft/musicxml/musicxml.py
ScoreDraft/musicxml/xlink.py
ScoreDraft/musicxml/xml.py
ScoreDraft-1.0.11.dist-info/METADATA
ScoreDraft-1.0.11.dist-info/WHEEL
ScoreDraft-1.0.11.dist-info/entry_points.txt
ScoreDraft-1.0.11.dist-info/top_level.txt
ScoreDraft-1.0.11.dist-info/RECORD
